mercariGetter/Library/mercariConfig.py
mercariGetter/Library/mercariDataController.py
mercariGetter/Library/mercariException.py
mercariGetter/Library/mercariGetterGlobals.py
mercariGetter-1.0.22.dist-info/METADATA
mercariGetter-1.0.22.dist-info/PKG-INFO-FreedomCry
mercariGetter-1.0.22.dist-info/SOURCES-FreedomCry.txt
mercariGetter-1.0.22.dist-info/WHEEL
mercariGetter-1.0.22.dist-info/requires-FreedomCry.txt
mercariGetter-1.0.22.dist-info/top_level.txt
mercariGetter-1.0.22.dist-info/RECORD
