Metadata-Version: 2.1
Name: mercariGetter
Version: 1.0.22
Summary: Mercari data collection package
Home-page: https://github.com/kaioman/mercariGetter.git
Author: Unchain Works
Author-email: kajin0318@gmail.com
License: BSD-3-Clause
Keywords: mercari
Platform: UNKNOWN
Classifier: Development Status :: 5 - Production/Stable
Classifier: License :: OSI Approved :: BSD License
Classifier: Programming Language :: Python
Classifier: Programming Language :: Python :: 3
Classifier: Programming Language :: Python :: 3.4
Classifier: Programming Language :: Python :: 3.5
Classifier: Programming Language :: Python :: 3.6
Classifier: Topic :: Database
Classifier: Topic :: Software Development :: Libraries :: Python Modules
Requires-Dist: beautifulsoup4 (==4.10.0)
Requires-Dist: bs4 (==0.0.1)
Requires-Dist: requests (==2.26.0)
Requires-Dist: requests-html (==0.10.0)
Requires-Dist: lxml (==4.6.3)
Requires-Dist: numpy (==1.19.5)
Requires-Dist: pandas (==1.3.3)
Requires-Dist: Django (==3.2.9)
Requires-Dist: selenium (==3.141.0)
Requires-Dist: LibHanger
Requires-Dist: Scrapinger
